filemagick/__main__.py
filemagick-0.1.0.dist-info/entry_points.txt
filemagick-0.1.0.dist-info/LICENSE
filemagick-0.1.0.dist-info/WHEEL
filemagick-0.1.0.dist-info/METADATA
filemagick-0.1.0.dist-info/RECORD
